{
  "version": "5.0.0",
  "release": false,
  "init_size": [
    1000,
    800
  ],
  "geo_info": {
    "locate": [
      116.400,
      39.910
    ],
    "eastern": true,
    "southern": false
  },
  "tooltip": {
    "anchor_bias": [
      90,
      50
    ],
    "visible": true
  },
  "layout": {
    "zoom_step": 1,
    "precision": 0.001,
    "init_window_size": 30,
    "min_window_size": 8,
    "min_grid_gap": 20,
    "max_grid_level": 10,
    "grid_convert_factor": 5
  },
  "animation": {
    "duration": 1000,
    "delay": 0,
    "easing": "linear"
  },
  "record": {
    "compatible_index": 1,
    "max_record": 1000
  }
}